KassStorager/__init__.py
KassStorager/Storager.py
KassStorager/StoragerAwsS3.py
KassStorager/StoragerOs.py
kassstorager-1.0.0.dist-info/LICENSE
kassstorager-1.0.0.dist-info/METADATA
kassstorager-1.0.0.dist-info/WHEEL
kassstorager-1.0.0.dist-info/RECORD
