Metadata-Version: 2.1
Name: KassStorager
Version: 1.0.0
Summary: Biblioteca para gerenciamento de diretórios e arquivos
Author: kassio douglas
Author-email: kass.doug@gmail.com.br
Requires-Python: >=3.11,<4.0
Classifier: Development Status :: 5 - Production/Stable
Classifier: Natural Language :: Portuguese (Brazilian)
Classifier: Programming Language :: Python :: 3
Classifier: Programming Language :: Python :: 3.11
Classifier: Programming Language :: Python :: 3.12
